offers_check_marketplaces/__init__.py
offers_check_marketplaces/__main__.py
offers_check_marketplaces/data_processor.py
offers_check_marketplaces/database_manager.py
offers_check_marketplaces/error_handling.py
offers_check_marketplaces/excel_tools.py
offers_check_marketplaces/license_manager.py
offers_check_marketplaces/marketplace_client.py
offers_check_marketplaces/marketplace_config.py
offers_check_marketplaces/models.py
offers_check_marketplaces/search_engine.py
offers_check_marketplaces/server.py
offers_check_marketplaces/statistics.py
offers_check_marketplaces/user_data_manager.py
offers_check_marketplaces_mcp_2025-0.1.12.dist-info/METADATA
offers_check_marketplaces_mcp_2025-0.1.12.dist-info/WHEEL
offers_check_marketplaces_mcp_2025-0.1.12.dist-info/entry_points.txt
offers_check_marketplaces_mcp_2025-0.1.12.dist-info/licenses/LICENSE
offers_check_marketplaces_mcp_2025-0.1.12.dist-info/RECORD
