Metadata-Version: 2.4
Name: offers-check-marketplaces-mcp-2025
Version: 0.1.12
Summary: MCP server for automated product search and price comparison across multiple marketplaces with integrated license management
Project-URL: Homepage, https://github.com/yourusername/offers-check-marketplaces-mcp
Project-URL: Repository, https://github.com/yourusername/offers-check-marketplaces-mcp
Project-URL: Documentation, https://github.com/yourusername/offers-check-marketplaces-mcp#readme
Project-URL: Bug Tracker, https://github.com/yourusername/offers-check-marketplaces-mcp/issues
Author-email: Your Name <your.email@example.com>
Maintainer-email: Your Name <your.email@example.com>
License: MIT
License-File: LICENSE
Keywords: automation,e-commerce,marketplace,mcp,price-comparison
Classifier: Development Status :: 4 - Beta
Classifier: Intended Audience :: Developers
Classifier: License :: OSI Approved :: MIT License
Classifier: Operating System :: OS Independent
Classifier: Programming Language :: Python :: 3
Classifier: Programming Language :: Python :: 3.10
Classifier: Programming Language :: Python :: 3.11
Classifier: Programming Language :: Python :: 3.12
Classifier: Programming Language :: Python :: 3.13
Classifier: Topic :: Internet :: WWW/HTTP :: Dynamic Content
Classifier: Topic :: Office/Business :: Financial :: Point-Of-Sale
Classifier: Topic :: Software Development :: Libraries :: Python Modules
Requires-Python: >=3.10
Requires-Dist: aiohttp>=3.8.0
Requires-Dist: aiosqlite>=0.19.0
Requires-Dist: anyio>=3.7.0
Requires-Dist: click>=8.1.3
Requires-Dist: mcp>=1.7.1
Requires-Dist: openpyxl>=3.1.0
Requires-Dist: pandas>=2.0.0
Requires-Dist: pydantic>=2.0.0
Requires-Dist: requests>=2.28.0
Requires-Dist: starlette>=0.28.0
Requires-Dist: uvicorn>=0.34.2
Provides-Extra: dev
Requires-Dist: build>=0.10.0; extra == 'dev'
Requires-Dist: debugpy; extra == 'dev'
Requires-Dist: mcp[cli]>=1.7.1; extra == 'dev'
Requires-Dist: pytest-asyncio; extra == 'dev'
Requires-Dist: pytest>=8.0; extra == 'dev'
Requires-Dist: twine>=4.0.0; extra == 'dev'
